<annotation>
	<folder>frames</folder>
	<filename>frame12997.jpg</filename>
	<path>H:\myspace\PokaYoke\frames\frame12997.jpg</path>
	<source>
		<database>Unknown</database>
	</source>
	<size>
		<width>1280</width>
		<height>720</height>
		<depth>3</depth>
	</size>
	<segmented>0</segmented>
	<object>
		<name>battery</name>
		<pose>Unspecified</pose>
		<truncated>0</truncated>
		<difficult>0</difficult>
		<bndbox>
			<xmin>188</xmin>
			<ymin>12</ymin>
			<xmax>1000</xmax>
			<ymax>622</ymax>
		</bndbox>
	</object>
	<object>
		<name>pos_connected</name>
		<pose>Unspecified</pose>
		<truncated>0</truncated>
		<difficult>0</difficult>
		<bndbox>
			<xmin>120</xmin>
			<ymin>286</ymin>
			<xmax>436</xmax>
			<ymax>474</ymax>
		</bndbox>
	</object>
	<object>
		<name>neg_connected</name>
		<pose>Unspecified</pose>
		<truncated>0</truncated>
		<difficult>0</difficult>
		<bndbox>
			<xmin>639</xmin>
			<ymin>5</ymin>
			<xmax>757</xmax>
			<ymax>126</ymax>
		</bndbox>
	</object>
</annotation>
