<annotation>
	<folder>frames</folder>
	<filename>frame192238.jpg</filename>
	<path>H:\myspace\PokaYoke\frames\frame192238.jpg</path>
	<source>
		<database>Unknown</database>
	</source>
	<size>
		<width>1280</width>
		<height>720</height>
		<depth>3</depth>
	</size>
	<segmented>0</segmented>
	<object>
		<name>battery</name>
		<pose>Unspecified</pose>
		<truncated>0</truncated>
		<difficult>0</difficult>
		<bndbox>
			<xmin>361</xmin>
			<ymin>156</ymin>
			<xmax>980</xmax>
			<ymax>630</ymax>
		</bndbox>
	</object>
	<object>
		<name>pos_disconnected</name>
		<pose>Unspecified</pose>
		<truncated>0</truncated>
		<difficult>0</difficult>
		<bndbox>
			<xmin>221</xmin>
			<ymin>304</ymin>
			<xmax>493</xmax>
			<ymax>503</ymax>
		</bndbox>
	</object>
	<object>
		<name>neg_disconnected</name>
		<pose>Unspecified</pose>
		<truncated>0</truncated>
		<difficult>0</difficult>
		<bndbox>
			<xmin>745</xmin>
			<ymin>186</ymin>
			<xmax>856</xmax>
			<ymax>266</ymax>
		</bndbox>
	</object>
</annotation>
