<annotation>
	<folder>frames</folder>
	<filename>frame61170.jpg</filename>
	<path>H:\myspace\PokaYoke\frames\frame61170.jpg</path>
	<source>
		<database>Unknown</database>
	</source>
	<size>
		<width>1280</width>
		<height>720</height>
		<depth>3</depth>
	</size>
	<segmented>0</segmented>
	<object>
		<name>battery</name>
		<pose>Unspecified</pose>
		<truncated>0</truncated>
		<difficult>0</difficult>
		<bndbox>
			<xmin>406</xmin>
			<ymin>133</ymin>
			<xmax>1031</xmax>
			<ymax>651</ymax>
		</bndbox>
	</object>
	<object>
		<name>pos_connected</name>
		<pose>Unspecified</pose>
		<truncated>0</truncated>
		<difficult>0</difficult>
		<bndbox>
			<xmin>457</xmin>
			<ymin>128</ymin>
			<xmax>666</xmax>
			<ymax>294</ymax>
		</bndbox>
	</object>
	<object>
		<name>neg_connected</name>
		<pose>Unspecified</pose>
		<truncated>0</truncated>
		<difficult>0</difficult>
		<bndbox>
			<xmin>851</xmin>
			<ymin>302</ymin>
			<xmax>1041</xmax>
			<ymax>476</ymax>
		</bndbox>
	</object>
</annotation>
