<annotation>
	<folder>frames</folder>
	<filename>frame17483.jpg</filename>
	<path>H:\myspace\PokaYoke\frames\frame17483.jpg</path>
	<source>
		<database>Unknown</database>
	</source>
	<size>
		<width>1280</width>
		<height>720</height>
		<depth>3</depth>
	</size>
	<segmented>0</segmented>
	<object>
		<name>battery</name>
		<pose>Unspecified</pose>
		<truncated>0</truncated>
		<difficult>0</difficult>
		<bndbox>
			<xmin>144</xmin>
			<ymin>30</ymin>
			<xmax>1104</xmax>
			<ymax>604</ymax>
		</bndbox>
	</object>
	<object>
		<name>pos_connected</name>
		<pose>Unspecified</pose>
		<truncated>0</truncated>
		<difficult>0</difficult>
		<bndbox>
			<xmin>845</xmin>
			<ymin>369</ymin>
			<xmax>1156</xmax>
			<ymax>548</ymax>
		</bndbox>
	</object>
	<object>
		<name>neg_connected</name>
		<pose>Unspecified</pose>
		<truncated>0</truncated>
		<difficult>0</difficult>
		<bndbox>
			<xmin>61</xmin>
			<ymin>353</ymin>
			<xmax>328</xmax>
			<ymax>505</ymax>
		</bndbox>
	</object>
	<object>
		<name>neg_touched</name>
		<pose>Unspecified</pose>
		<truncated>0</truncated>
		<difficult>0</difficult>
		<bndbox>
			<xmin>120</xmin>
			<ymin>208</ymin>
			<xmax>474</xmax>
			<ymax>653</ymax>
		</bndbox>
	</object>
</annotation>
